<?xml version="1.0" encoding="utf-8" ?>
<TemamaTradingConfig>
  <PublicKey></PublicKey>
  <SecretKey></SecretKey>
  <BaseCurrency>btc</BaseCurrency>
  <FundCurrency>uah</FundCurrency>
  <MinBaseToTrade>0.0001</MinBaseToTrade>
  <MinFundToTrade>5.0</MinFundToTrade>
  <ExecuteInterval>30</ExecuteInterval> <!-- Interval between bot iterations in seconds-->
  <SellFarPercent>1.4</SellFarPercent>
  <SellNearPercent>0.7</SellNearPercent>
  <BuyNearPercent>0.7</BuyNearPercent>
  <BuyFarPercent>1.4</BuyFarPercent>
  <AllowAutoBalanceTrades>true</AllowAutoBalanceTrades>
  <ImbalanceValue>3.0</ImbalanceValue> <!-- if (BTC*Price)/UAH>ImbalanceValue or UAH/(BTC*Price)>ImbalanceValue - need to buy or sell to make (BTC*Price)~=UAH -->
</TemamaTradingConfig>
